hivemind_voice_relay/__init__.py
hivemind_voice_relay/__main__.py
hivemind_voice_relay/service.py
hivemind_voice_relay/version.py
HiveMind_voice_relay-1.0.1.dist-info/LICENSE
HiveMind_voice_relay-1.0.1.dist-info/METADATA
HiveMind_voice_relay-1.0.1.dist-info/WHEEL
HiveMind_voice_relay-1.0.1.dist-info/entry_points.txt
HiveMind_voice_relay-1.0.1.dist-info/top_level.txt
HiveMind_voice_relay-1.0.1.dist-info/RECORD
