Metadata-Version: 2.1
Name: HiveMind-voice-relay
Version: 1.0.1
Summary: Hivemind Voice Relay
Home-page: https://github.com/JarbasHiveMind/HiveMind-voice-relay
Author: jarbasAI
Author-email: jarbasai@mailfence.com
License: Apache2
Platform: UNKNOWN
Requires-Dist: hivemind-bus-client>=0.0.4
Requires-Dist: ovos-audio
Requires-Dist: ovos-simple-listener<1.0.0,>=0.0.3
Requires-Dist: ovos-microphone-plugin-alsa
Requires-Dist: ovos-vad-plugin-silero
Requires-Dist: ovos-stt-plugin-server
Requires-Dist: ovos-tts-plugin-server
Requires-Dist: click
Requires-Dist: pybase64
